[{"map":{"tps":1,"time":"16:32:34.622"}},{"map":{"tps":1,"time":"16:32:38.962"}},{"map":{"tps":1,"time":"16:32:42.827"}},{"map":{"tps":1,"time":"16:32:46.926"}},{"map":{"tps":1,"time":"16:32:47.463"}},{"map":{"tps":1,"time":"16:32:51.763"}},{"map":{"tps":1,"time":"16:32:52.433"}},{"map":{"tps":1,"time":"16:32:54.761"}},{"map":{"tps":1,"time":"16:32:55.318"}},{"map":{"tps":1,"time":"16:32:55.426"}},{"map":{"tps":1,"time":"16:32:55.548"}},{"map":{"tps":1,"time":"16:32:55.633"}},{"map":{"tps":1,"time":"16:32:55.638"}},{"map":{"tps":1,"time":"16:32:55.737"}},{"map":{"tps":1,"time":"16:32:55.93"}},{"map":{"tps":1,"time":"16:32:56.749"}},{"map":{"tps":1,"time":"16:32:58.924"}},{"map":{"tps":1,"time":"16:32:59.022"}},{"map":{"tps":1,"time":"16:32:59.175"}},{"map":{"tps":1,"time":"16:32:59.221"}},{"map":{"tps":1,"time":"16:32:59.35"}},{"map":{"tps":1,"time":"16:32:59.527"}},{"map":{"tps":1,"time":"16:32:59.532"}},{"map":{"tps":1,"time":"16:32:59.742"}},{"map":{"tps":1,"time":"16:32:59.753"}},{"map":{"tps":1,"time":"16:32:59.861"}},{"map":{"tps":1,"time":"16:32:59.88"}},{"map":{"tps":1,"time":"16:33:00.022"}},{"map":{"tps":1,"time":"16:33:00.032"}},{"map":{"tps":1,"time":"16:33:00.045"}},{"map":{"tps":1,"time":"16:33:00.049"}},{"map":{"tps":1,"time":"16:33:00.129"}},{"map":{"tps":1,"time":"16:33:00.133"}},{"map":{"tps":1,"time":"16:33:00.154"}},{"map":{"tps":1,"time":"16:33:00.232"}},{"map":{"tps":1,"time":"16:33:00.935"}},{"map":{"tps":1,"time":"16:33:01.142"}},{"map":{"tps":1,"time":"16:33:01.162"}},{"map":{"tps":1,"time":"16:33:01.232"}},{"map":{"tps":1,"time":"16:33:01.422"}},{"map":{"tps":1,"time":"16:33:01.529"}},{"map":{"tps":1,"time":"16:33:01.618"}},{"map":{"tps":1,"time":"16:33:01.64"}},{"map":{"tps":1,"time":"16:33:01.763"}},{"map":{"tps":1,"time":"16:33:01.766"}},{"map":{"tps":1,"time":"16:33:01.837"}},{"map":{"tps":1,"time":"16:33:02.251"}},{"map":{"tps":1,"time":"16:33:02.836"}},{"map":{"tps":1,"time":"16:33:02.865"}},{"map":{"tps":1,"time":"16:33:02.875"}},{"map":{"tps":1,"time":"16:33:02.925"}},{"map":{"tps":1,"time":"16:33:03.774"}},{"map":{"tps":1,"time":"16:33:03.777"}},{"map":{"tps":1,"time":"16:33:04.133"}},{"map":{"tps":1,"time":"16:33:04.138"}},{"map":{"tps":1,"time":"16:33:04.243"}},{"map":{"tps":1,"time":"16:33:04.333"}},{"map":{"tps":1,"time":"16:33:04.422"}},{"map":{"tps":1,"time":"16:33:04.557"}},{"map":{"tps":1,"time":"16:33:04.631"}},{"map":{"tps":1,"time":"16:33:06.733"}},{"map":{"tps":1,"time":"16:33:06.921"}},{"map":{"tps":1,"time":"16:33:06.943"}},{"map":{"tps":1,"time":"16:33:07.121"}},{"map":{"tps":1,"time":"16:33:07.357"}},{"map":{"tps":1,"time":"16:33:07.436"}},{"map":{"tps":1,"time":"16:33:07.541"}},{"map":{"tps":1,"time":"16:33:07.623"}},{"map":{"tps":1,"time":"16:33:07.629"}},{"map":{"tps":1,"time":"16:33:07.637"}},{"map":{"tps":1,"time":"16:33:07.833"}},{"map":{"tps":1,"time":"16:33:08.291"}},{"map":{"tps":1,"time":"16:33:08.324"}},{"map":{"tps":1,"time":"16:33:08.332"}},{"map":{"tps":1,"time":"16:33:08.422"}},{"map":{"tps":1,"time":"16:33:08.433"}},{"map":{"tps":1,"time":"16:33:08.537"}},{"map":{"tps":1,"time":"16:33:08.789"}},{"map":{"tps":1,"time":"16:33:08.832"}},{"map":{"tps":1,"time":"16:33:08.848"}},{"map":{"tps":1,"time":"16:33:08.924"}},{"map":{"tps":1,"time":"16:33:08.966"}},{"map":{"tps":1,"time":"16:33:09.025"}},{"map":{"tps":1,"time":"16:33:09.058"}},{"map":{"tps":1,"time":"16:33:09.121"}},{"map":{"tps":1,"time":"16:33:09.155"}},{"map":{"tps":1,"time":"16:33:12.43"}},{"map":{"tps":1,"time":"16:33:12.451"}},{"map":{"tps":1,"time":"16:33:12.522"}},{"map":{"tps":1,"time":"16:33:13.724"}},{"map":{"tps":1,"time":"16:33:14.527"}},{"map":{"tps":1,"time":"16:33:16.721"}},{"map":{"tps":1,"time":"16:33:16.725"}},{"map":{"tps":1,"time":"16:33:16.895"}},{"map":{"tps":1,"time":"16:33:16.921"}},{"map":{"tps":1,"time":"16:33:16.939"}},{"map":{"tps":1,"time":"16:33:17.023"}}]